[
  {
    "id": "2121",
    "parent_id": "5",
    "name": "Вінницька область "
  },
  {
    "id": "2123",
    "parent_id": "5",
    "name": "Волинська область "
  },
  {
    "id": "2126",
    "parent_id": "5",
    "name": "Дніпропетровська область "
  },
  {
    "id": "2134",
    "parent_id": "5",
    "name": "Донецька область"
  },
  {
    "id": "2147",
    "parent_id": "5",
    "name": "Житомирська область"
  },
  {
    "id": "2152",
    "parent_id": "5",
    "name": "Закарпатська область "
  },
  {
    "id": "2155",
    "parent_id": "5",
    "name": "Запорізька область"
  },
  {
    "id": "2160",
    "parent_id": "5",
    "name": "Івано-Франківська область"
  },
  {
    "id": "115",
    "parent_id": "5",
    "name": "Київ"
  },
  {
    "id": "2164",
    "parent_id": "5",
    "name": "Київська область"
  },
  {
    "id": "2169",
    "parent_id": "5",
    "name": "Кіровоградська область"
  },
  {
    "id": "2173",
    "parent_id": "5",
    "name": "Луганська область"
  },
  {
    "id": "2180",
    "parent_id": "5",
    "name": "Львівська область"
  },
  {
    "id": "2185",
    "parent_id": "5",
    "name": "Миколаївська область"
  },
  {
    "id": "2188",
    "parent_id": "5",
    "name": "Одеська область"
  },
  {
    "id": "2193",
    "parent_id": "5",
    "name": "Полтавська область"
  },
  {
    "id": "2198",
    "parent_id": "5",
    "name": "Рівненська область"
  },
  {
    "id": "2200",
    "parent_id": "5",
    "name": "Сумська область"
  },
  {
    "id": "2204",
    "parent_id": "5",
    "name": "Тернопільська область"
  },
  {
    "id": "2206",
    "parent_id": "5",
    "name": "Харківська область"
  },
  {
    "id": "2209",
    "parent_id": "5",
    "name": "Херсонська область"
  },
  {
    "id": "2212",
    "parent_id": "5",
    "name": "Хмельницька область"
  },
  {
    "id": "2216",
    "parent_id": "5",
    "name": "Черкаська область"
  },
  {
    "id": "2220",
    "parent_id": "5",
    "name": "Чернівецька область"
  },
  {
    "id": "2224",
    "parent_id": "5",
    "name": "Чернігівська область"
  }
]
